gepref/__init__.py
gepref/list.py
gepref/preprocessor.py
gepref/py.typed
gepref/step.py
gepref-0.1.2.dist-info/LICENSE
gepref-0.1.2.dist-info/WHEEL
gepref-0.1.2.dist-info/METADATA
gepref-0.1.2.dist-info/RECORD
