Metadata-Version: 2.1
Name: gepref
Version: 0.1.2
Summary: GEneral PREprocessing Framework (gepref)
Author-email: Juan Lara <julara@unal.edu.co>
Requires-Python: >3.10
Requires-Dist: jedi-language-server ; extra == "dev"
Requires-Dist: mypy ; extra == "dev"
Requires-Dist: pytest ; extra == "dev"
Requires-Dist: ruff ; extra == "dev"
Requires-Dist: flit ; extra == "dev"
Requires-Dist: sphinx ; extra == "dev"
Requires-Dist: sphinx-book-theme ; extra == "dev"
Requires-Dist: myst_parser ; extra == "dev"
Provides-Extra: dev
